README.txt
setup.py
solaris_ssh/__init__.py
solaris_ssh.egg-info/PKG-INFO
solaris_ssh.egg-info/SOURCES.txt
solaris_ssh.egg-info/dependency_links.txt
solaris_ssh.egg-info/entry_points.txt
solaris_ssh.egg-info/top_level.txt