Metadata-Version: 1.0
Name: solaris-ssh
Version: 0.1
Summary: Python3 library to run SSH in parallel
Home-page: UNKNOWN
Author: UNKNOWN
Author-email: UNKNOWN
License: MIT
Keywords: ssh
Platform: UNKNOWN
